Metadata-Version: 1.0
Name: discogs-finder
Version: 1.1
Summary: FIND Every Release in your collection
Home-page: https://github.com/tim6her/discogs_finder
Author: Tim B. Herbstrith
Author-email: UNKNOWN
License: MIT
Platform: UNKNOWN
